treerequests/__init__.py
treerequests/args.py
treerequests/logger.py
treerequests/session.py
treerequests/tree.py
treerequests/useragents.py
treerequests-0.0.16.dist-info/licenses/LICENSE
treerequests-0.0.16.dist-info/METADATA
treerequests-0.0.16.dist-info/WHEEL
treerequests-0.0.16.dist-info/top_level.txt
treerequests-0.0.16.dist-info/RECORD
