Metadata-Version: 2.4
Name: treerequests
Version: 0.0.16
Summary: A wrapper for requests for integration with html tree parsers
Author-email: Dominik Stanisław Suchora <hexderm@gmail.com>
License: GPLv3
Project-URL: Homepage, https://github.com/TUVIMEN/treerequests
Keywords: requests,reliq,wrapper
Classifier: Development Status :: 4 - Beta
Classifier: License :: OSI Approved :: GNU General Public License v3 (GPLv3)
Classifier: Operating System :: OS Independent
Classifier: Programming Language :: Python :: 3
Classifier: Programming Language :: Python :: 3.8
Classifier: Programming Language :: Python :: 3.9
Classifier: Programming Language :: Python :: 3.10
Classifier: Programming Language :: Python :: 3.11
Classifier: Programming Language :: Python :: 3.12
Classifier: Programming Language :: Python :: 3.13
Classifier: Programming Language :: Python :: 3 :: Only
Requires-Python: >=3.8
License-File: LICENSE
Provides-Extra: cookies
Requires-Dist: browser_cookie3; extra == "cookies"
Provides-Extra: bs4
Requires-Dist: bs4; extra == "bs4"
Provides-Extra: lxml
Requires-Dist: lxml; extra == "lxml"
Provides-Extra: html5-parser
Requires-Dist: html5_parser; extra == "html5-parser"
Provides-Extra: selectolax
Requires-Dist: selectolax; extra == "selectolax"
Provides-Extra: reliq
Requires-Dist: reliq; extra == "reliq"
Dynamic: license-file
